lazy_imports/__init__.py
lazy_imports/lazy_module.py
lazy_imports/py.typed
lazy_imports/try_import.py
lazy_imports/util.py
lazy_imports/v0/__init__.py
lazy_imports/v0/lazy_imports.py
lazy_imports-1.0.0.dist-info/licenses/LICENSE
tests/__init__.py
tests/test__init__.py
tests/test_try_import.py
lazy_imports-1.0.0.dist-info/METADATA
lazy_imports-1.0.0.dist-info/WHEEL
lazy_imports-1.0.0.dist-info/top_level.txt
lazy_imports-1.0.0.dist-info/RECORD
