Metadata-Version: 2.4
Name: lazy_imports
Version: 1.0.0
Summary: Tool to support lazy imports
Author: Pascal Bachor
Author-email: lazy-imports.vista851@passmail.net
Maintainer: Pascal Bachor
Project-URL: Changelog, https://github.com/bachorp/lazy-imports/blob/HEAD/CHANGELOG.md
Project-URL: Bug Tracker, https://github.com/bachorp/lazy-imports/issues
Project-URL: Source Code, https://github.com/bachorp/lazy-imports
Keywords: import imports lazy
Classifier: Development Status :: 5 - Production/Stable
Classifier: Intended Audience :: Developers
Classifier: License :: OSI Approved :: Apache Software License
Classifier: Programming Language :: Python :: 3
Classifier: Programming Language :: Python :: 3.9
Classifier: Programming Language :: Python :: 3.10
Classifier: Programming Language :: Python :: 3.11
Classifier: Programming Language :: Python :: 3.12
Classifier: Programming Language :: Python :: 3.13
Classifier: Programming Language :: Python :: 3 :: Only
Classifier: Topic :: Software Development
Classifier: Topic :: Software Development :: Libraries
Classifier: Topic :: Software Development :: Libraries :: Python Modules
Classifier: Operating System :: OS Independent
Requires-Python: >=3.9
License-File: LICENSE
Provides-Extra: checking
Requires-Dist: black; extra == "checking"
Requires-Dist: flake8; extra == "checking"
Requires-Dist: isort; extra == "checking"
Requires-Dist: mdformat; extra == "checking"
Requires-Dist: pydocstyle; extra == "checking"
Requires-Dist: mypy; extra == "checking"
Requires-Dist: pylint; extra == "checking"
Requires-Dist: pylintfileheader; extra == "checking"
Provides-Extra: testing
Requires-Dist: pytest; extra == "testing"
Requires-Dist: packaging; extra == "testing"
Provides-Extra: all
Requires-Dist: mdformat; extra == "all"
Requires-Dist: isort; extra == "all"
Requires-Dist: mypy; extra == "all"
Requires-Dist: pydocstyle; extra == "all"
Requires-Dist: pylintfileheader; extra == "all"
Requires-Dist: pytest; extra == "all"
Requires-Dist: pylint; extra == "all"
Requires-Dist: flake8; extra == "all"
Requires-Dist: packaging; extra == "all"
Requires-Dist: black; extra == "all"
Dynamic: author
Dynamic: author-email
Dynamic: classifier
Dynamic: description
Dynamic: description-content-type
Dynamic: keywords
Dynamic: license-file
Dynamic: maintainer
Dynamic: project-url
Dynamic: provides-extra
Dynamic: requires-python
Dynamic: summary
